coreTeamMetrics/__init__.py
coreTeamMetrics/main.py
coreTeamMetrics-3.0.2.dist-info/METADATA
coreTeamMetrics-3.0.2.dist-info/WHEEL
coreTeamMetrics-3.0.2.dist-info/top_level.txt
coreTeamMetrics-3.0.2.dist-info/RECORD
