Metadata-Version: 2.1
Name: coreTeamMetrics
Version: 3.0.2
Summary: A Prometheus metrics collector for runtime metrics
Home-page: UNKNOWN
Author: core-team
Author-email: coreteam@example.com
License: UNKNOWN
Platform: UNKNOWN
Requires-Python: >=3.6
Requires-Dist: prometheus-client
